web3evm/__init__.py
web3evm/web3evm.py
web3evm-0.1.3.dist-info/METADATA
web3evm-0.1.3.dist-info/WHEEL
web3evm-0.1.3.dist-info/top_level.txt
web3evm-0.1.3.dist-info/RECORD
