Metadata-Version: 2.1
Name: web3evm
Version: 0.1.3
Summary: evm utilities
Home-page: 
Author: bryains
Author-email: 
Classifier: Programming Language :: Python :: 3
Classifier: License :: OSI Approved :: MIT License
Classifier: Operating System :: OS Independent
Requires-Python: >=3.7
